{"results": [{"id": "ethbnt", "text": "ETHBNT"}, {"id": "npxsbnt", "text": "NPXSBNT"}, {"id": "batbnt", "text": "BATBNT"}, {"id": "enjbnt", "text": "ENJBNT"}, {"id": "daibnt", "text": "DAIBNT"}, {"id": "locbnt", "text": "LOCBNT"}, {"id": "bnbbnt", "text": "BNBBNT"}, {"id": "rcnbnt", "text": "RCNBNT"}, {"id": "powrbnt", "text": "POWRBNT"}, {"id": "mkrbnt", "text": "MKRBNT"}, {"id": "kncbnt", "text": "KNCBNT"}, {"id": "tknbnt", "text": "TKNBNT"}, {"id": "omgbnt", "text": "OMGBNT"}, {"id": "eursbnt", "text": "EURSBNT"}, {"id": "poabnt", "text": "POABNT"}, {"id": "elfbnt", "text": "ELFBNT"}, {"id": "gnobnt", "text": "GNOBNT"}, {"id": "vibbnt", "text": "VIBBNT"}, {"id": "antbnt", "text": "ANTBNT"}, {"id": "dgdbnt", "text": "DGDBNT"}, {"id": "rembnt", "text": "REMBNT"}, {"id": "gtobnt", "text": "GTOBNT"}, {"id": "xdcebnt", "text": "XDCEBNT"}, {"id": "reqbnt", "text": "REQBNT"}, {"id": "mftbnt", "text": "MFTBNT"}, {"id": "rlcbnt", "text": "RLCBNT"}, {"id": "usdbbnt", "text": "USDB / BNT"}, {"id": "mdtbnt", "text": "MDTBNT"}, {"id": "mtlbnt", "text": "MTLBNT"}, {"id": "agribnt", "text": "AGRIBNT"}, {"id": "rdnbnt", "text": "RDNBNT"}, {"id": "wbtc", "text": "WBTC"}, {"id": "sanbnt", "text": "SANBNT"}, {"id": "sntbnt", "text": "SNTBNT"}, {"id": "madbnt", "text": "MADBNT"}, {"id": "j8tbnt", "text": "J8TBNT"}, {"id": "plrbnt", "text": "PLRBNT"}, {"id": "fxcbnt", "text": "FXCBNT"}, {"id": "tixbnt", "text": "TIXBNT"}, {"id": "realbnt", "text": "REALBNT"}, {"id": "eletbnt", "text": "ELETBNT"}, {"id": "databnt", "text": "DATABNT"}, {"id": "rvtbnt", "text": "RVTBNT"}, {"id": "mrphbnt", "text": "MRPHBNT"}, {"id": "fkxbnt", "text": "FKXBNT"}, {"id": "flixxbnt", "text": "FLIXXBNT"}, {"id": "upbnt", "text": "UPBNT"}, {"id": "drgnbnt", "text": "DRGNBNT"}, {"id": "mybbnt", "text": "MYBBNT"}, {"id": "mfgbnt", "text": "MFGBNT"}, {"id": "ftxbnt", "text": "FTXBNT"}, {"id": "hedgbnt", "text": "HEDGBNT"}, {"id": "mntpbnt", "text": "MNTPBNT"}, {"id": "bnt-usd", "text": "BNT-USD"}, {"id": "abxbnt", "text": "ABXBNT"}, {"id": "srnbnt", "text": "SRNBNT"}, {"id": "xbpbnt", "text": "XBPBNT"}, {"id": "dtrcbnt", "text": "DTRCBNT"}, {"id": "uptbnt", "text": "UPTBNT"}, {"id": "ceekbnt", "text": "CEEKBNT"}, {"id": "veebnt", "text": "VEEBNT"}, {"id": "ethusdb", "text": "ETHUSDB"}, {"id": "ziptbnt", "text": "ZIPTBNT"}, {"id": "x8xbnt", "text": "X8XBNT"}, {"id": "usdqbnt", "text": "USDQBNT"}, {"id": "mrgbnt", "text": "MRGBNT"}, {"id": "cmctbnt", "text": "CMCTBNT"}, {"id": "ldcbnt", "text": "LDCBNT"}, {"id": "canbnt", "text": "CANBNT"}, {"id": "amnbnt", "text": "AMNBNT"}, {"id": "rblxbnt", "text": "RBLXBNT"}, {"id": "locibnt", "text": "LOCIBNT"}, {"id": "wingsbnt", "text": "WINGSBNT"}, {"id": "boxxbnt", "text": "BOXXBNT"}, {"id": "sclbnt", "text": "SCLBNT"}, {"id": "metusdb", "text": "METUSDB"}, {"id": "xnkbnt", "text": "XNKBNT"}, {"id": "amplbnt", "text": "AMPLBNT"}, {"id": "wandbnt", "text": "WANDBNT"}, {"id": "jrtusdb", "text": "JRTUSDB"}, {"id": "qdaobnt", "text": "QDAOBNT"}, {"id": "ongbnt", "text": "ONGBNT"}, {"id": "daiusdb", "text": "DAIUSDB"}, {"id": "taasbnt", "text": "TAASBNT"}, {"id": "spdbnt", "text": "SPDBNT"}, {"id": "aucbnt", "text": "AUCBNT"}, {"id": "rstbnt", "text": "RSTBNT"}, {"id": "tbxbnt", "text": "TBXBNT"}, {"id": "susdusdb", "text": "sUSDUSDB"}, {"id": "edgbnt", "text": "EDGBNT"}, {"id": "trstbnt", "text": "TRSTBNT"}, {"id": "bcsbnt", "text": "BCSBNT"}, {"id": "refbnt", "text": "REFBNT"}, {"id": "sxlbnt", "text": "SXLBNT"}, {"id": "tnsbnt", "text": "TNSBNT"}, {"id": "svdbnt", "text": "SVDBNT"}, {"id": "xpatbnt", "text": "XPATBNT"}, {"id": "efoodbnt", "text": "EFOODBNT"}, {"id": "catbnt", "text": "CATBNT"}, {"id": "cvtbnt", "text": "CVTBNT"}, {"id": "cotbnt", "text": "COTBNT"}, {"id": "stacbnt", "text": "STACBNT"}, {"id": "evobnt", "text": "EVOBNT"}, {"id": "danbnt", "text": "DANBNT"}, {"id": "aixbnt", "text": "AIXBNT"}, {"id": "atsbnt", "text": "ATSBNT"}, {"id": "prtlbnt", "text": "PRTLBNT"}, {"id": "c20bnt", "text": "C20BNT"}, {"id": "zrxusdb", "text": "ZRXUSDB"}, {"id": "nexousdb", "text": "NEXOUSDB"}, {"id": "omgusdb", "text": "OMGUSDB"}, {"id": "loomusdb", "text": "LOOMUSDB"}, {"id": "kncusdb", "text": "KNCUSDB"}, {"id": "renusdb", "text": "RENUSDB"}, {"id": "batusdb", "text": "BATUSDB"}, {"id": "kinbnt", "text": "KINBNT"}, {"id": "usdtusdb", "text": "USDTUSDB"}, {"id": "baxbnt", "text": "BAXBNT"}, {"id": "usdcusdb", "text": "USDCUSDB"}, {"id": "repuxbnt", "text": "REPUXBNT"}, {"id": "tusdusdb", "text": "TUSDUSDB"}, {"id": "tbcusdb", "text": "TBCUSDB"}, {"id": "mlnusdb", "text": "MLNUSDB"}, {"id": "tbcbnt", "text": "TBCBNT"}, {"id": "eszbnt", "text": "ESZBNT"}, {"id": "stormbnt", "text": "STORMBNT"}, {"id": "bbobnt", "text": "BBOBNT"}, {"id": "enjusdb", "text": "ENJUSDB"}, {"id": "gesbnt", "text": "GESBNT"}, {"id": "acdbnt", "text": "ACDBNT"}, {"id": "morphbnt", "text": "MORPHBNT"}, {"id": "omnisbnt", "text": "OMNISBNT"}, {"id": "mgtbnt", "text": "MGTBNT"}, {"id": "mkrusdb", "text": "MKRUSDB"}, {"id": "4xbbnt", "text": "4XBBNT"}, {"id": "ankbnt", "text": "ANKBNT"}, {"id": "linkusdb", "text": "LINKUSDB"}, {"id": "powrusdb", "text": "POWRUSDB"}, {"id": "dzarusdb", "text": "DZARUSDB"}, {"id": "hotbnt", "text": "HOTBNT"}, {"id": "rlcusdb", "text": "RLCUSDB"}, {"id": "repusdb", "text": "REPUSDB"}, {"id": "snxusdb", "text": "SNXUSDB"}, {"id": "busdusdb", "text": "BUSDUSDB"}, {"id": "nmrusdb", "text": "NMRUSDB"}, {"id": "emcobnt", "text": "EMCOBNT"}, {"id": "sigbnt", "text": "SIGBNT"}, {"id": "mgtbnt_1", "text": "MGTBNT"}, {"id": "clnbnt", "text": "CLNBNT"}]}