{"results": [{"id": "hex", "text": "HEX"}, {"id": "usdc", "text": "USDC"}, {"id": "mkr", "text": "MKR"}, {"id": "dai", "text": "DAI"}, {"id": "pnk", "text": "PNK"}, {"id": "seth", "text": "sETH"}, {"id": "weth", "text": "WETH"}, {"id": "tkn", "text": "TKN"}, {"id": "bat", "text": "BAT"}, {"id": "jrt", "text": "JRT"}, {"id": "link", "text": "LINK"}, {"id": "lend", "text": "LEND"}, {"id": "xchf", "text": "XCHF"}, {"id": "spank", "text": "SPANK"}, {"id": "xio", "text": "XIO"}, {"id": "nmr", "text": "NMR"}, {"id": "wbtc", "text": "WBTC"}, {"id": "rep", "text": "REP"}, {"id": "gno", "text": "GNO"}, {"id": "rcn", "text": "RCN"}, {"id": "ring", "text": "RING"}, {"id": "anj", "text": "ANJ"}, {"id": "ubt", "text": "UBT"}, {"id": "sai", "text": "SAI"}, {"id": "tusd", "text": "TUSD"}, {"id": "realtoken-16200-fullerton-ave-detroit-mi", "text": "REALTOKEN-16200-FULLERTON-AVE-DETROIT-MI"}, {"id": "realtoken-10024-10028-appoline-st-detroit-mi", "text": "REALTOKEN-10024-10028-APPOLINE-ST-DETROIT-MI"}, {"id": "thedao", "text": "TheDAO"}, {"id": "lqd", "text": "LQD"}, {"id": "ult(st)", "text": "ULT (ST)"}, {"id": "rdn", "text": "RDN"}, {"id": "zcc", "text": "ZCC"}, {"id": "dzar", "text": "DZAR"}, {"id": "realtoken-8342-schaefer-hwy-detroit-mi", "text": "REALTOKEN-8342-SCHAEFER-HWY-DETROIT-MI"}, {"id": "socks", "text": "SOCKS"}, {"id": "pan", "text": "PAN"}, {"id": "isai", "text": "iSAI"}, {"id": "fun", "text": "FUN"}, {"id": "h3x", "text": "H3X"}, {"id": "snx", "text": "SNX"}, {"id": "realtoken-9336-patton-st-detroit-mi", "text": "REALTOKEN-9336-PATTON-ST-DETROIT-MI"}, {"id": "ant", "text": "ANT"}, {"id": "mln", "text": "MLN"}, {"id": "realtoken-20200-lesure-st-detroit-mi", "text": "REALTOKEN-20200-LESURE-ST-DETROIT-MI"}, {"id": "ick", "text": "ICK"}, {"id": "knc", "text": "KNC"}, {"id": "band", "text": "BAND"}, {"id": "buidl", "text": "BUIDL"}, {"id": "oxt", "text": "OXT"}, {"id": "hot", "text": "HOT"}, {"id": "adai", "text": "aDAI"}, {"id": "realtoken-9943-marlowe-st-detroit-mi", "text": "REALTOKEN-9943-MARLOWE-ST-DETROIT-MI"}, {"id": "sethold", "text": "sETH old"}, {"id": "hedg", "text": "HEDG"}, {"id": "auc", "text": "AUC"}, {"id": "data", "text": "DATA"}, {"id": "enj", "text": "ENJ"}, {"id": "realtoken-5942-audubon-rd-detroit-mi", "text": "REALTOKEN-5942-AUDUBON-RD-DETROIT-MI"}, {"id": "zrx", "text": "ZRX"}, {"id": "blt", "text": "BLT"}, {"id": "publx", "text": "PUBLX"}, {"id": "snt", "text": "SNT"}, {"id": "gen", "text": "GEN"}, {"id": "btu", "text": "BTU"}, {"id": "ren", "text": "REN"}, {"id": "vamp", "text": "VAMP"}, {"id": "raise", "text": "RAISE"}, {"id": "dgx", "text": "DGX"}, {"id": "tape", "text": "TAPE"}, {"id": "pas", "text": "PAS"}, {"id": "mps", "text": "MPS"}, {"id": "skull", "text": "SKULL"}, {"id": "btc++", "text": "BTC++"}, {"id": "alex", "text": "ALEX"}, {"id": "dip", "text": "DIP"}, {"id": "tgbp", "text": "TGBP"}, {"id": "mana", "text": "MANA"}, {"id": "cncc", "text": "CNCC"}, {"id": "almx", "text": "ALMX"}, {"id": "ocomp$150put080720", "text": "oCOMP $150 Put 08/07/20"}, {"id": "uma", "text": "UMA"}, {"id": "taud", "text": "TAUD"}, {"id": "thkd", "text": "THKD"}, {"id": "tcad", "text": "TCAD"}, {"id": "haut", "text": "HAUT"}, {"id": "realtoken-18276-appoline-st-detroit-mi", "text": "REALTOKEN-18276-APPOLINE-ST-DETROIT-MI"}, {"id": "realtoken-25097-andover-dr-dearborn-mi", "text": "REALTOKEN-25097-ANDOVER-DR-DEARBORN-MI"}, {"id": "pasg", "text": "PASG"}, {"id": "lpt", "text": "LPT"}, {"id": "cot", "text": "COT"}, {"id": "bnt", "text": "BNT"}, {"id": "gst2", "text": "GST2"}, {"id": "trst", "text": "TRST"}, {"id": "vnm", "text": "VNM"}, {"id": "ast", "text": "AST"}, {"id": "ampl", "text": "AMPL"}, {"id": "csai", "text": "cSAI"}, {"id": "vee", "text": "VEE"}, {"id": "tons", "text": "TONS"}, {"id": "zomb", "text": "ZOMB"}, {"id": "fame", "text": "FAME"}, {"id": "kerman", "text": "KERMAN"}, {"id": "realtoken-15634-liberal-st-detroit-mi", "text": "REALTOKEN-15634-LIBERAL-ST-DETROIT-MI"}, {"id": "susd", "text": "sUSD"}, {"id": "cami", "text": "CAMI"}, {"id": "bcdt", "text": "BCDT"}, {"id": "chai", "text": "CHAI"}, {"id": "bnb", "text": "BNB"}, {"id": "oeth$180put092520", "text": "oETH $180 Put 09/25/20"}, {"id": "ngnt", "text": "NGNT"}, {"id": "owl", "text": "OWL"}, {"id": "$pew", "text": "$PEW"}, {"id": "rsr", "text": "RSR"}, {"id": "0xbtc", "text": "0xBTC"}, {"id": "mtb18", "text": "MTB18"}, {"id": "hue", "text": "HUE"}, {"id": "seeds", "text": "SEEDS"}, {"id": "forcer", "text": "FORCER"}, {"id": "realtoken-18900-mansfield-st-detroit-mi", "text": "REALTOKEN-18900-MANSFIELD-ST-DETROIT-MI"}, {"id": "susdold", "text": "sUSD old"}, {"id": "mtb19", "text": "MTB19"}, {"id": "calvin", "text": "CALVIN"}, {"id": "fnd", "text": "FND"}, {"id": "flip", "text": "FLIP"}, {"id": "julien", "text": "JULIEN"}, {"id": "vxv", "text": "VXV"}, {"id": "udao", "text": "UDAO"}, {"id": "cdai", "text": "cDAI"}, {"id": "storj", "text": "STORJ"}, {"id": "sent", "text": "SENT"}, {"id": "colr", "text": "COLR"}, {"id": "mcx", "text": "MCX"}, {"id": "paul", "text": "PAUL"}, {"id": "matic", "text": "MATIC"}, {"id": "pass", "text": "PASS"}, {"id": "lev", "text": "LEV"}, {"id": "alxo", "text": "ALXO"}, {"id": "scott", "text": "SCOTT"}, {"id": "rpl", "text": "RPL"}, {"id": "slp", "text": "SLP"}, {"id": "saturn", "text": "SATURN"}, {"id": "st", "text": "ST"}, {"id": "jsh", "text": "JSH"}, {"id": "dc", "text": "DC"}, {"id": "rdr", "text": "RDR"}, {"id": "bee", "text": "BEE"}, {"id": "tom", "text": "TOM"}, {"id": "undt", "text": "UNDT"}, {"id": "foam", "text": "FOAM"}, {"id": "stx", "text": "STX"}, {"id": "swt", "text": "SWT"}, {"id": "ssle", "text": "SSLE"}, {"id": "nexo", "text": "NEXO"}, {"id": "bugs", "text": "BUGS"}, {"id": "fet", "text": "FET"}, {"id": "rlc", "text": "RLC"}, {"id": "saturn", "text": "SATURN"}, {"id": "test", "text": "TEST"}, {"id": "cel", "text": "CEL"}, {"id": "lrc", "text": "LRC"}, {"id": "pygoz", "text": "PYGOZ"}, {"id": "minds", "text": "MINDS"}, {"id": "yin", "text": "YIN"}, {"id": "dank", "text": "DANK"}, {"id": "hyd", "text": "HYD"}, {"id": "tokenfactory", "text": "TOKENFACTORY"}, {"id": "ocdai", "text": "ocDai"}, {"id": "oeth$230put072420", "text": "oETH $230 Put 07/24/20"}, {"id": "isla", "text": "ISLA"}, {"id": "yumi", "text": "YUMI"}, {"id": "wgm", "text": "WGM"}, {"id": "boi", "text": "BOI"}, {"id": "ethusdadl4", "text": "ETHUSDADL4"}, {"id": "tusdold", "text": "TUSD old"}, {"id": "kern", "text": "KERN"}, {"id": "dmex", "text": "DMEX"}, {"id": "oeth$100put042420", "text": "oETH $100 Put 04/24/20"}, {"id": "ting", "text": "TING"}, {"id": "ship", "text": "SHIP"}, {"id": "scb", "text": "SCB"}, {"id": "xyo", "text": "XYO"}, {"id": "cre", "text": "CRE"}, {"id": "oeth$240put061920", "text": "oETH $240 Put 06/19/20"}, {"id": "iotx", "text": "IOTX"}, {"id": "roobee", "text": "ROOBEE"}, {"id": "cvc", "text": "CVC"}, {"id": "gcash", "text": "GCASH"}, {"id": "immo", "text": "IMMO"}, {"id": "time", "text": "TIME"}, {"id": "pov", "text": "POV"}, {"id": "hour", "text": "HOUR"}, {"id": "paxg", "text": "PAXG"}, {"id": "oethcall1400thshare092520", "text": "oETH Call 1/400th share 09/25/20 "}, {"id": "shuf", "text": "SHUF"}, {"id": "cnac", "text": "CNAC"}, {"id": "sp", "text": "Sp"}, {"id": "uni-v1", "text": "UNI-V1"}, {"id": "oeth$150put042420", "text": "oETH $150 Put 04/24/20"}, {"id": "math", "text": "MATH"}, {"id": "lst", "text": "LST"}, {"id": "oeth$150put052920", "text": "oETH $150 Put 05/29/20"}, {"id": "col", "text": "COL"}, {"id": "ldr", "text": "LDR"}, {"id": "ftm", "text": "FTM"}, {"id": "can", "text": "CAN"}, {"id": "cvl", "text": "CVL"}, {"id": "drt", "text": "DRT"}, {"id": "burn", "text": "BURN"}, {"id": "dth", "text": "DTH"}, {"id": "bbdd", "text": "BBDD"}, {"id": "sub", "text": "SUB"}, {"id": "usds", "text": "USDS"}, {"id": "grid", "text": "GRID"}, {"id": "fsnt", "text": "FSNT"}, {"id": "pdc", "text": "PDC"}, {"id": "ch-zg1235d", "text": "CH-ZG1235d"}, {"id": "sin", "text": "SIN"}, {"id": "idex", "text": "IDEX"}, {"id": "erc20", "text": "ERC20"}, {"id": "oeth$220put071720", "text": "oETH $220 Put 07/17/20"}, {"id": "mbc", "text": "MBC"}, {"id": "hum", "text": "HUM"}, {"id": "zipt", "text": "ZIPT"}, {"id": "bcpt", "text": "BCPT"}, {"id": "tbc", "text": "TBC"}, {"id": "boom", "text": "BOOM"}, {"id": "vld", "text": "VLD"}, {"id": "drj", "text": "DRJ"}, {"id": "esh", "text": "ESH"}, {"id": "usdb", "text": "USDB"}, {"id": "mco", "text": "MCO"}, {"id": "dank", "text": "DANK"}, {"id": "aps", "text": "APS"}, {"id": "san", "text": "SAN"}, {"id": "kin", "text": "KIN"}, {"id": "exrn", "text": "EXRN"}, {"id": "qnt", "text": "QNT"}, {"id": "ceth", "text": "cETH"}, {"id": "lsd", "text": "LSD"}, {"id": "xs2", "text": "XS2"}, {"id": "credit", "text": "CREDIT"}, {"id": "rwrd", "text": "RWRD"}]}