{
 "results": [
  {
   "id": "mkr",
   "text": "MKR"
  },
  {
   "id": "dai",
   "text": "DAI"
  },
  {
   "id": "tusd",
   "text": "TUSD"
  },
  {
   "id": "bat",
   "text": "BAT"
  },
  {
   "id": "xchf",
   "text": "XCHF"
  },
  {
   "id": "rep",
   "text": "REP"
  },
  {
   "id": "snx",
   "text": "SNX"
  },
  {
   "id": "dgx",
   "text": "DGX"
  },
  {
   "id": "susd",
   "text": "sUSD"
  },
  {
   "id": "zrx",
   "text": "ZRX"
  },
  {
   "id": "blt",
   "text": "BLT"
  },
  {
   "id": "weth",
   "text": "WETH"
  },
  {
   "id": "tkn",
   "text": "TKN"
  },
  {
   "id": "ant",
   "text": "ANT"
  },
  {
   "id": "spank",
   "text": "SPANK"
  },
  {
   "id": "link",
   "text": "LINK"
  },
  {
   "id": "fun",
   "text": "FUN"
  },
  {
   "id": "rlc",
   "text": "RLC"
  },
  {
   "id": "nmr",
   "text": "NMR"
  },
  {
   "id": "pnk",
   "text": "PNK"
  },
  {
   "id": "bnt",
   "text": "BNT"
  },
  {
   "id": "rdn",
   "text": "RDN"
  },
  {
   "id": "ult",
   "text": "ULT"
  },
  {
   "id": "snt",
   "text": "SNT"
  },
  {
   "id": "nexo",
   "text": "NEXO"
  },
  {
   "id": "grid",
   "text": "GRID"
  },
  {
   "id": "dgd",
   "text": "DGD"
  },
  {
   "id": "usdc",
   "text": "USDC"
  },
  {
   "id": "hot",
   "text": "HOT"
  },
  {
   "id": "knc",
   "text": "KNC"
  },
  {
   "id": "mana",
   "text": "MANA"
  },
  {
   "id": "enj",
   "text": "ENJ"
  },
  {
   "id": "foam",
   "text": "FOAM"
  },
  {
   "id": "loom",
   "text": "LOOM"
  },
  {
   "id": "swt",
   "text": "SWT"
  },
  {
   "id": "ft",
   "text": "FT"
  },
  {
   "id": "bee",
   "text": "BEE"
  },
  {
   "id": "c20",
   "text": "C20"
  },
  {
   "id": "auc",
   "text": "AUC"
  },
  {
   "id": "fnd",
   "text": "FND"
  },
  {
   "id": "0xbtc",
   "text": "0xBTC"
  },
  {
   "id": "bnb",
   "text": "BNB"
  },
  {
   "id": "lpt",
   "text": "LPT"
  },
  {
   "id": "req",
   "text": "REQ"
  }
 ]
}